stock_data_reader/stockreader.py
stock_data_reader-1.0.7.dist-info/DESCRIPTION.rst
stock_data_reader-1.0.7.dist-info/METADATA
stock_data_reader-1.0.7.dist-info/RECORD
stock_data_reader-1.0.7.dist-info/WHEEL
stock_data_reader-1.0.7.dist-info/entry_points.txt
stock_data_reader-1.0.7.dist-info/metadata.json
stock_data_reader-1.0.7.dist-info/top_level.txt
