Metadata-Version: 2.0
Name: stock-data-reader
Version: 1.0.7
Summary: A Python Package to get the stock data price for a company.
Home-page: https://github.com/mukulkkumar/stock-data
Author: Mukul Kumar
Author-email: mukulkkumarr@gmail.com
License: MIT
Platform: UNKNOWN
Classifier: License :: OSI Approved :: MIT License
Classifier: Programming Language :: Python :: 3
Classifier: Programming Language :: Python :: 3.7
Requires-Dist: requests
